flask_uls/__init__.py
flask_uls/py.typed
flask_uls/static/flask-uls.css
flask_uls/static/jquery-3.4.1.js
flask_uls/static/jquery-3.4.1.min.js
flask_uls/static/jquery.uls/css/jquery.uls.css
flask_uls/static/jquery.uls/css/jquery.uls.grid.css
flask_uls/static/jquery.uls/css/jquery.uls.lcd.css
flask_uls/static/jquery.uls/css/jquery.uls.mobile.css
flask_uls/static/jquery.uls/images/close.png
flask_uls/static/jquery.uls/images/close.svg
flask_uls/static/jquery.uls/images/language.png
flask_uls/static/jquery.uls/images/language.svg
flask_uls/static/jquery.uls/images/search.png
flask_uls/static/jquery.uls/images/search.svg
flask_uls/static/jquery.uls/src/jquery.uls.core.js
flask_uls/static/jquery.uls/src/jquery.uls.data.js
flask_uls/static/jquery.uls/src/jquery.uls.data.utils.js
flask_uls/static/jquery.uls/src/jquery.uls.languagefilter.js
flask_uls/static/jquery.uls/src/jquery.uls.lcd.js
flask_uls/templates/uls/footer.html
flask_uls/templates/uls/head.html
Flask_ULS-0.2.0.dist-info/COPYING
Flask_ULS-0.2.0.dist-info/METADATA
Flask_ULS-0.2.0.dist-info/WHEEL
Flask_ULS-0.2.0.dist-info/top_level.txt
Flask_ULS-0.2.0.dist-info/RECORD
